// class version 60.0 (60)
// access flags 0x21
public class org/autotest/StackAr {

  // compiled from: StackAr.java
  // access flags 0x19
  public final static INNERCLASS java/lang/invoke/MethodHandles$Lookup java/lang/invoke/MethodHandles Lookup

  // access flags 0x1A
  private final static I DEFAULT_CAPACITY = 10

  // access flags 0x12
  private final [Ljava/lang/Object; elems

  // access flags 0x2
  private I readIndex

  // access flags 0x1
  public <init>()V
   L0
    LINENUMBER 17 L0
    ALOAD 0
    BIPUSH 10
    INVOKESPECIAL org/autotest/StackAr.<init> (I)V
   L1
    LINENUMBER 18 L1
    RETURN
   L2
    LOCALVARIABLE this Lorg/autotest/StackAr; L0 L2 0
    MAXSTACK = 2
    MAXLOCALS = 1

  // access flags 0x1
  public <init>(I)V throws java/lang/IllegalArgumentException 
   L0
    LINENUMBER 20 L0
    ALOAD 0
    INVOKESPECIAL java/lang/Object.<init> ()V
   L1
    LINENUMBER 14 L1
    ALOAD 0
    ICONST_M1
    PUTFIELD org/autotest/StackAr.readIndex : I
   L2
    LINENUMBER 21 L2
    ILOAD 1
    IFGE L3
   L4
    LINENUMBER 22 L4
    NEW java/lang/IllegalArgumentException
    DUP
    INVOKESPECIAL java/lang/IllegalArgumentException.<init> ()V
    ATHROW
   L3
    LINENUMBER 24 L3
   FRAME FULL [org/autotest/StackAr I] []
    ALOAD 0
    ILOAD 1
    ANEWARRAY java/lang/Object
    PUTFIELD org/autotest/StackAr.elems : [Ljava/lang/Object;
   L5
    LINENUMBER 25 L5
    RETURN
   L6
    LOCALVARIABLE this Lorg/autotest/StackAr; L0 L6 0
    LOCALVARIABLE capacity I L0 L6 1
    MAXSTACK = 2
    MAXLOCALS = 2

  // access flags 0x1
  public repOK()Z
  @Lrandoop/CheckRep;()
    TRYCATCHBLOCK L0 L1 L2 java/lang/Exception
    TRYCATCHBLOCK L0 L1 L2 java/lang/Error
   L0
    LINENUMBER 40 L0
    ALOAD 0
    GETFIELD org/autotest/StackAr.elems : [Ljava/lang/Object;
    IFNULL L3
    ALOAD 0
    GETFIELD org/autotest/StackAr.readIndex : I
    ICONST_M1
    IF_ICMPLT L3
    ALOAD 0
    GETFIELD org/autotest/StackAr.readIndex : I
    ALOAD 0
    GETFIELD org/autotest/StackAr.elems : [Ljava/lang/Object;
    ARRAYLENGTH
    IF_ICMPGE L3
    ALOAD 0
    GETFIELD org/autotest/StackAr.elems : [Ljava/lang/Object;
   L4
    LINENUMBER 42 L4
    INVOKESTATIC java/util/Arrays.stream ([Ljava/lang/Object;)Ljava/util/stream/Stream;
    ALOAD 0
    GETFIELD org/autotest/StackAr.readIndex : I
    ICONST_1
    IADD
    I2L
    INVOKEINTERFACE java/util/stream/Stream.skip (J)Ljava/util/stream/Stream; (itf)
    INVOKEDYNAMIC test()Ljava/util/function/Predicate; [
      // handle kind 0x6 : INVOKESTATIC
      java/lang/invoke/LambdaMetafactory.metafactory(Ljava/lang/invoke/MethodHandles$Lookup;Ljava/lang/String;Ljava/lang/invoke/MethodType;Ljava/lang/invoke/MethodType;Ljava/lang/invoke/MethodHandle;Ljava/lang/invoke/MethodType;)Ljava/lang/invoke/CallSite;
      // arguments:
      (Ljava/lang/Object;)Z, 
      // handle kind 0x6 : INVOKESTATIC
      java/util/Objects.isNull(Ljava/lang/Object;)Z, 
      (Ljava/lang/Object;)Z
    ]
    INVOKEINTERFACE java/util/stream/Stream.allMatch (Ljava/util/function/Predicate;)Z (itf)
    IFEQ L3
    ICONST_1
    GOTO L1
   L3
   FRAME FULL [org/autotest/StackAr] []
    ICONST_0
   L1
    LINENUMBER 40 L1
   FRAME FULL [org/autotest/StackAr] [I]
    IRETURN
   L2
    LINENUMBER 43 L2
   FRAME FULL [org/autotest/StackAr] [java/lang/Throwable]
    ASTORE 1
   L5
    LINENUMBER 44 L5
    GETSTATIC java/lang/System.err : Ljava/io/PrintStream;
    LDC "ERROR en el m\u00c3\u00a9todo repOK."
    INVOKEVIRTUAL java/io/PrintStream.println (Ljava/lang/String;)V
   L6
    LINENUMBER 45 L6
    ALOAD 1
    INVOKEVIRTUAL java/lang/Throwable.printStackTrace ()V
   L7
    LINENUMBER 46 L7
    ICONST_0
    IRETURN
   L8
    LOCALVARIABLE e Ljava/lang/Throwable; L5 L8 1
    LOCALVARIABLE this Lorg/autotest/StackAr; L0 L8 0
    MAXSTACK = 3
    MAXLOCALS = 2

  // access flags 0x1
  public size()I
   L0
    LINENUMBER 51 L0
    ALOAD 0
    GETFIELD org/autotest/StackAr.readIndex : I
    ICONST_1
    IADD
    IRETURN
   L1
    LOCALVARIABLE this Lorg/autotest/StackAr; L0 L1 0
    MAXSTACK = 2
    MAXLOCALS = 1

  // access flags 0x1
  public isEmpty()Z
   L0
    LINENUMBER 55 L0
    ALOAD 0
    INVOKEVIRTUAL org/autotest/StackAr.size ()I
    IFNE L1
    ICONST_1
    GOTO L2
   L1
   FRAME FULL [org/autotest/StackAr] []
    ICONST_0
   L2
   FRAME FULL [org/autotest/StackAr] [I]
    IRETURN
   L3
    LOCALVARIABLE this Lorg/autotest/StackAr; L0 L3 0
    MAXSTACK = 1
    MAXLOCALS = 1

  // access flags 0x1
  public isFull()Z
   L0
    LINENUMBER 59 L0
    ALOAD 0
    INVOKEVIRTUAL org/autotest/StackAr.size ()I
    ALOAD 0
    GETFIELD org/autotest/StackAr.elems : [Ljava/lang/Object;
    ARRAYLENGTH
    IF_ICMPNE L1
    ICONST_1
    GOTO L2
   L1
   FRAME FULL [org/autotest/StackAr] []
    ICONST_0
   L2
   FRAME FULL [org/autotest/StackAr] [I]
    IRETURN
   L3
    LOCALVARIABLE this Lorg/autotest/StackAr; L0 L3 0
    MAXSTACK = 2
    MAXLOCALS = 1

  // access flags 0x1
  public push(Ljava/lang/Object;)V throws java/lang/IllegalStateException 
   L0
    LINENUMBER 63 L0
    ALOAD 0
    INVOKEVIRTUAL org/autotest/StackAr.isFull ()Z
    IFEQ L1
   L2
    LINENUMBER 64 L2
    NEW java/lang/IllegalStateException
    DUP
    INVOKESPECIAL java/lang/IllegalStateException.<init> ()V
    ATHROW
   L1
    LINENUMBER 66 L1
   FRAME FULL [org/autotest/StackAr java/lang/Object] []
    ALOAD 0
    DUP
    GETFIELD org/autotest/StackAr.readIndex : I
    ICONST_1
    IADD
    PUTFIELD org/autotest/StackAr.readIndex : I
   L3
    LINENUMBER 67 L3
    ALOAD 0
    GETFIELD org/autotest/StackAr.elems : [Ljava/lang/Object;
    ALOAD 0
    GETFIELD org/autotest/StackAr.readIndex : I
    ALOAD 1
    AASTORE
   L4
    LINENUMBER 68 L4
    RETURN
   L5
    LOCALVARIABLE this Lorg/autotest/StackAr; L0 L5 0
    LOCALVARIABLE o Ljava/lang/Object; L0 L5 1
    MAXSTACK = 3
    MAXLOCALS = 2

  // access flags 0x1
  public pop()Ljava/lang/Object; throws java/lang/IllegalStateException 
   L0
    LINENUMBER 71 L0
    ALOAD 0
    INVOKEVIRTUAL org/autotest/StackAr.isEmpty ()Z
    IFEQ L1
   L2
    LINENUMBER 72 L2
    NEW java/lang/IllegalStateException
    DUP
    INVOKESPECIAL java/lang/IllegalStateException.<init> ()V
    ATHROW
   L1
    LINENUMBER 74 L1
   FRAME FULL [org/autotest/StackAr] []
    ALOAD 0
    INVOKEVIRTUAL org/autotest/StackAr.top ()Ljava/lang/Object;
    ASTORE 1
   L3
    LINENUMBER 75 L3
    ALOAD 0
    GETFIELD org/autotest/StackAr.elems : [Ljava/lang/Object;
    ALOAD 0
    GETFIELD org/autotest/StackAr.readIndex : I
    ACONST_NULL
    AASTORE
   L4
    LINENUMBER 76 L4
    ALOAD 0
    DUP
    GETFIELD org/autotest/StackAr.readIndex : I
    ICONST_1
    ISUB
    PUTFIELD org/autotest/StackAr.readIndex : I
   L5
    LINENUMBER 77 L5
    ALOAD 1
    ARETURN
   L6
    LOCALVARIABLE this Lorg/autotest/StackAr; L0 L6 0
    LOCALVARIABLE rv Ljava/lang/Object; L3 L6 1
    MAXSTACK = 3
    MAXLOCALS = 2

  // access flags 0x1
  public top()Ljava/lang/Object; throws java/lang/IllegalStateException 
   L0
    LINENUMBER 81 L0
    ALOAD 0
    INVOKEVIRTUAL org/autotest/StackAr.isEmpty ()Z
    IFEQ L1
   L2
    LINENUMBER 82 L2
    NEW java/lang/IllegalStateException
    DUP
    INVOKESPECIAL java/lang/IllegalStateException.<init> ()V
    ATHROW
   L1
    LINENUMBER 84 L1
   FRAME FULL [org/autotest/StackAr] []
    ALOAD 0
    GETFIELD org/autotest/StackAr.elems : [Ljava/lang/Object;
    ALOAD 0
    GETFIELD org/autotest/StackAr.readIndex : I
    AALOAD
    ASTORE 1
   L3
    LINENUMBER 85 L3
    ALOAD 1
    ARETURN
   L4
    LOCALVARIABLE this Lorg/autotest/StackAr; L0 L4 0
    LOCALVARIABLE rv Ljava/lang/Object; L3 L4 1
    MAXSTACK = 2
    MAXLOCALS = 2

  // access flags 0x1
  public hashCode()I
   L0
    LINENUMBER 90 L0
    BIPUSH 31
    ISTORE 1
   L1
    LINENUMBER 91 L1
    ICONST_1
    ISTORE 2
   L2
    LINENUMBER 92 L2
    BIPUSH 31
    ILOAD 2
    IMUL
    ALOAD 0
    GETFIELD org/autotest/StackAr.elems : [Ljava/lang/Object;
    INVOKESTATIC java/util/Arrays.hashCode ([Ljava/lang/Object;)I
    IADD
    ISTORE 2
   L3
    LINENUMBER 93 L3
    BIPUSH 31
    ILOAD 2
    IMUL
    ALOAD 0
    GETFIELD org/autotest/StackAr.readIndex : I
    IADD
    ISTORE 2
   L4
    LINENUMBER 94 L4
    ILOAD 2
    IRETURN
   L5
    LOCALVARIABLE this Lorg/autotest/StackAr; L0 L5 0
    LOCALVARIABLE prime I L1 L5 1
    LOCALVARIABLE result I L2 L5 2
    MAXSTACK = 2
    MAXLOCALS = 3

  // access flags 0x1
  public equals(Ljava/lang/Object;)Z
   L0
    LINENUMBER 99 L0
    ALOAD 0
    ALOAD 1
    IF_ACMPNE L1
   L2
    LINENUMBER 100 L2
    ICONST_1
    IRETURN
   L1
    LINENUMBER 101 L1
   FRAME FULL [org/autotest/StackAr java/lang/Object] []
    ALOAD 1
    IFNONNULL L3
   L4
    LINENUMBER 102 L4
    ICONST_0
    IRETURN
   L3
    LINENUMBER 103 L3
   FRAME FULL [org/autotest/StackAr java/lang/Object] []
    ALOAD 0
    INVOKEVIRTUAL java/lang/Object.getClass ()Ljava/lang/Class;
    ALOAD 1
    INVOKEVIRTUAL java/lang/Object.getClass ()Ljava/lang/Class;
    IF_ACMPEQ L5
   L6
    LINENUMBER 104 L6
    ICONST_0
    IRETURN
   L5
    LINENUMBER 105 L5
   FRAME FULL [org/autotest/StackAr java/lang/Object] []
    ALOAD 1
    CHECKCAST org/autotest/StackAr
    ASTORE 2
   L7
    LINENUMBER 106 L7
    ALOAD 0
    GETFIELD org/autotest/StackAr.elems : [Ljava/lang/Object;
    ALOAD 2
    GETFIELD org/autotest/StackAr.elems : [Ljava/lang/Object;
    INVOKESTATIC java/util/Arrays.equals ([Ljava/lang/Object;[Ljava/lang/Object;)Z
    IFNE L8
   L9
    LINENUMBER 107 L9
    ICONST_0
    IRETURN
   L8
    LINENUMBER 108 L8
   FRAME FULL [org/autotest/StackAr java/lang/Object org/autotest/StackAr] []
    ALOAD 0
    GETFIELD org/autotest/StackAr.readIndex : I
    ALOAD 2
    GETFIELD org/autotest/StackAr.readIndex : I
    IF_ICMPEQ L10
   L11
    LINENUMBER 109 L11
    ICONST_0
    POP
    ICONST_1
    IRETURN
   L10
    LINENUMBER 110 L10
   FRAME FULL [org/autotest/StackAr java/lang/Object org/autotest/StackAr] []
    ICONST_1
    IRETURN
   L12
    LOCALVARIABLE this Lorg/autotest/StackAr; L0 L12 0
    LOCALVARIABLE obj Ljava/lang/Object; L0 L12 1
    LOCALVARIABLE other Lorg/autotest/StackAr; L7 L12 2
    MAXSTACK = 2
    MAXLOCALS = 3

  // access flags 0x1
  public toString()Ljava/lang/String;
   L0
    LINENUMBER 115 L0
    NEW java/lang/StringBuffer
    DUP
    INVOKESPECIAL java/lang/StringBuffer.<init> ()V
    ASTORE 1
   L1
    LINENUMBER 116 L1
    ALOAD 1
    LDC "["
    INVOKEVIRTUAL java/lang/StringBuffer.append (Ljava/lang/String;)Ljava/lang/StringBuffer;
    POP
   L2
    LINENUMBER 117 L2
    ICONST_0
    ISTORE 2
   L3
   FRAME FULL [org/autotest/StackAr java/lang/StringBuffer I] []
    ILOAD 2
    ALOAD 0
    GETFIELD org/autotest/StackAr.readIndex : I
    IF_ICMPGT L4
   L5
    LINENUMBER 118 L5
    ILOAD 2
    IFLE L6
   L7
    LINENUMBER 119 L7
    ALOAD 1
    LDC ","
    INVOKEVIRTUAL java/lang/StringBuffer.append (Ljava/lang/String;)Ljava/lang/StringBuffer;
    POP
   L6
    LINENUMBER 121 L6
   FRAME FULL [org/autotest/StackAr java/lang/StringBuffer I] []
    ALOAD 0
    GETFIELD org/autotest/StackAr.elems : [Ljava/lang/Object;
    ILOAD 2
    AALOAD
    ASTORE 3
   L8
    LINENUMBER 122 L8
    ALOAD 3
    INVOKESTATIC java/lang/String.valueOf (Ljava/lang/Object;)Ljava/lang/String;
    ASTORE 4
   L9
    LINENUMBER 123 L9
    ALOAD 1
    ALOAD 4
    INVOKEVIRTUAL java/lang/StringBuffer.append (Ljava/lang/String;)Ljava/lang/StringBuffer;
    POP
   L10
    LINENUMBER 117 L10
    IINC 2 1
    GOTO L3
   L4
    LINENUMBER 125 L4
   FRAME FULL [org/autotest/StackAr java/lang/StringBuffer I] []
    ALOAD 1
    LDC "]"
    INVOKEVIRTUAL java/lang/StringBuffer.append (Ljava/lang/String;)Ljava/lang/StringBuffer;
    POP
   L11
    LINENUMBER 126 L11
    ALOAD 1
    INVOKEVIRTUAL java/lang/StringBuffer.toString ()Ljava/lang/String;
    ARETURN
   L12
    LOCALVARIABLE o Ljava/lang/Object; L8 L10 3
    LOCALVARIABLE s Ljava/lang/String; L9 L10 4
    LOCALVARIABLE i I L3 L4 2
    LOCALVARIABLE this Lorg/autotest/StackAr; L0 L12 0
    LOCALVARIABLE b Ljava/lang/StringBuffer; L1 L12 1
    MAXSTACK = 2
    MAXLOCALS = 5
}

